optslope/__init__.py
optslope/models.py
optslope/plotting.py
optslope/slope.py
optslope/util.py
optslope-0.2.0.dist-info/LICENSE
optslope-0.2.0.dist-info/METADATA
optslope-0.2.0.dist-info/WHEEL
optslope-0.2.0.dist-info/top_level.txt
optslope-0.2.0.dist-info/zip-safe
optslope-0.2.0.dist-info/RECORD
