Metadata-Version: 2.1
Name: optslope
Version: 0.2.0
Summary: OptSlope - A tool for metabolic engineering, based on the OptSlope algorithm
Author-email: Elad Noor <elad.noor@weizmann.ac.il>, "Moritz E. Beber" <midnighter@posteo.net>
License: MIT License
Project-URL: repository, https://gitlab.com/elad.noor/optslope/
Project-URL: documentation, https://gitlab.com/elad.noor/optslope/README.md
Keywords: strain design,gene knockout,optimization,constraint-based
Classifier: Development Status :: 4 - Beta
Classifier: Intended Audience :: Science/Research
Classifier: Topic :: Scientific/Engineering :: Bio-Informatics
Classifier: Topic :: Scientific/Engineering :: Chemistry
Classifier: License :: OSI Approved :: MIT License
Classifier: Natural Language :: English
Classifier: Operating System :: OS Independent
Classifier: Programming Language :: Python :: 3 :: Only
Classifier: Programming Language :: Python :: 3.9
Classifier: Programming Language :: Python :: 3.10
Classifier: Programming Language :: Python :: 3.11
Classifier: Programming Language :: Python :: 3.12
Requires-Python: >=3.9
License-File: LICENSE
Requires-Dist: numpy ~=1.26
Requires-Dist: scipy ~=1.12
Requires-Dist: matplotlib ~=3.8
Requires-Dist: pandas ~=2.2
Requires-Dist: optlang ~=1.8
Requires-Dist: cobra ~=0.29
Provides-Extra: deployment
Requires-Dist: click ; extra == 'deployment'
Requires-Dist: click-log ; extra == 'deployment'
Requires-Dist: python-dateutil ; extra == 'deployment'
Requires-Dist: requests ; extra == 'deployment'
Provides-Extra: development
Requires-Dist: black ; extra == 'development'
Requires-Dist: isort ; extra == 'development'
Requires-Dist: flake8 ; extra == 'development'
Requires-Dist: safety ; extra == 'development'
Requires-Dist: tox ; extra == 'development'
Requires-Dist: twine ; extra == 'development'
Provides-Extra: test
Requires-Dist: pytest ; extra == 'test'
